{"charset":"utf-8","headers":{"content-type":"text/plain; charset=utf-8","plural-forms":"nplurals = 3; plural = (n % 10 === 1 && n % 100 !== 11 ? 0 : n % 10 >= 2 && n % 10 <= 4 && (n % 100 < 10 || n % 100 >= 20) ? 1 : 2);","language":"be","mime-version":"1.0","content-transfer-encoding":"8bit"},"translations":{"":{"":{"msgid":"","msgstr":["Content-Type: text/plain; charset=utf-8\nPlural-Forms: nplurals = 3; plural = (n % 10 === 1 && n % 100 !== 11 ? 0 : n % 10 >= 2 && n % 10 <= 4 && (n % 100 < 10 || n % 100 >= 20) ? 1 : 2);\nLanguage: be\nmime-version: 1.0\nContent-Transfer-Encoding: 8bit\n"]},"Home":{"msgid":"Home","msgstr":["Галоўная"]},"History":{"msgid":"History","msgstr":["Гісторыя"]},"Statistics":{"msgid":"Statistics","msgstr":["Статыстыка"]},"Favorite":{"msgid":"Favorite","msgstr":["Выбранае"]},"Country":{"msgid":"Country","msgstr":["Краіна"]},"City":{"msgid":"City","msgstr":["Горад"]},"Please choose country":{"msgid":"Please choose country","msgstr":["Спачатку выберыце краіну"]},"Vendor":{"msgid":"Vendor","msgstr":["Пастаўшчык"]},"Category":{"msgid":"Category","msgstr":["Катэгорыя"]},"Sub Category":{"msgid":"Sub Category","msgstr":["Падкатэгорыя"]},"Please choose category":{"msgid":"Please choose category","msgstr":["Спачатку выберыце катэгорыю"]},"Apply":{"msgid":"Apply","msgstr":["Прымяніць"]},"Search":{"msgid":"Search","msgstr":["Пошук"]}}}}